find_time/__init__.py
find_time/classes.py
find_time/main.py
find_time/parsing.py
find_time/utils.py
find_time-1.0.1.dist-info/LICENSE
find_time-1.0.1.dist-info/METADATA
find_time-1.0.1.dist-info/WHEEL
find_time-1.0.1.dist-info/entry_points.txt
find_time-1.0.1.dist-info/top_level.txt
find_time-1.0.1.dist-info/RECORD
