Metadata-Version: 2.1
Name: find-time
Version: 1.0.1
Summary: A simple tool for finding regular availability overlaps between event invitees.
Download-URL: https://github.com/csparker247/find-time
Author: Seth Parker
Author-email: csparker247@gmail.com
Classifier: Programming Language :: Python :: 3
Classifier: Programming Language :: Python :: 3.10
Classifier: Programming Language :: Python :: 3.11
Classifier: Programming Language :: Python :: 3.12
Classifier: Operating System :: OS Independent
Classifier: License :: OSI Approved :: MIT License
Requires-Python: >=3.10
License-File: LICENSE
Requires-Dist: lark
